comanda_daunov.py
comanda_daunov-1.0.0.dist-info/WHEEL
comanda_daunov-1.0.0.dist-info/METADATA
comanda_daunov-1.0.0.dist-info/RECORD
